hadal/__init__.py
hadal/custom_logger.py
hadal/faiss_search.py
hadal/huggingface_automodel.py
hadal/parallel_sentence_mining/margin_based/margin_based.py
hadal/parallel_sentence_mining/margin_based/margin_based_tools.py
hadal/tests/test_basic_imports.py
hadal/tests/test_package_imports.py
hadal/tests/testing_tools.py
hadal/tests/test_models/test_hf_automodel_encoding_convert.py
hadal/tests/test_models/test_hf_automodel_encoding_input.py
hadal/tests/test_models/test_hf_automodel_encoding_norm.py
hadal/tests/test_models/test_hf_automodel_encoding_output.py
hadal/tests/test_parallel_sentence_mining/test_minimal_example_margin_based.py
hadal-0.0.3.dist-info/METADATA
hadal-0.0.3.dist-info/WHEEL
hadal-0.0.3.dist-info/licenses/LICENSE
hadal-0.0.3.dist-info/RECORD
