Metadata-Version: 2.1
Name: hadal
Version: 0.0.3
Summary: Tool for mining/alignment parallel texts
Project-URL: Homepage, https://github.com/rggdmonk/hadal
Project-URL: Bug Reports, https://github.com/rggdmonk/hadal/issues
Project-URL: Source, https://github.com/rggdmonk/hadal
Author: Pavel Stepachev
Maintainer: Pavel Stepachev
License:                     GNU GENERAL PUBLIC LICENSE
License-File: LICENSE
Keywords: machine translation,parallel corpora,text alignment,text processing
Classifier: Development Status :: 3 - Alpha
Classifier: Topic :: Scientific/Engineering :: Artificial Intelligence
Requires-Python: >=3.10
Requires-Dist: tqdm
Requires-Dist: transformers>=4.0
Provides-Extra: dev
Requires-Dist: black>=23.11; extra == 'dev'
Requires-Dist: coverage>=7.3; extra == 'dev'
Requires-Dist: pytest-cov>=4.1; extra == 'dev'
Requires-Dist: pytest>=7.4; extra == 'dev'
Provides-Extra: docs
Requires-Dist: mkdocs-gen-files>=0.5.0; extra == 'docs'
Requires-Dist: mkdocs-literate-nav>=0.6.1; extra == 'docs'
Requires-Dist: mkdocs-material>=9.4; extra == 'docs'
Requires-Dist: mkdocs-section-index>=0.3.8; extra == 'docs'
Requires-Dist: mkdocstring-python>=1.7.3; extra == 'docs'
Requires-Dist: mkdocstrings>=0.23.0; extra == 'docs'
Requires-Dist: pymdown-extensions>=10.3.1; extra == 'docs'
